spacon/__init__.py
spacon/model.py
spacon/utils.py
spacon-0.1.3.dist-info/licenses/LICENSE
spacon-0.1.3.dist-info/METADATA
spacon-0.1.3.dist-info/WHEEL
spacon-0.1.3.dist-info/top_level.txt
spacon-0.1.3.dist-info/RECORD
