Metadata-Version: 2.4
Name: spacon
Version: 0.1.3
Summary: SpaCon: integrative analysis of spatial transcriptome and connectome
Home-page: https://github.com/quhaichao/SpaCon
Author: haichao
Author-email: qvhaichao@gmail.com
License: MIT
Classifier: Programming Language :: Python :: 3
Classifier: License :: OSI Approved :: MIT License
Classifier: Operating System :: OS Independent
Requires-Python: >=3.9
License-File: LICENSE
Requires-Dist: scanpy
Requires-Dist: numpy
Requires-Dist: tqdm
Requires-Dist: scipy
Requires-Dist: python-igraph
Requires-Dist: louvain
Requires-Dist: nibabel
Requires-Dist: alphashape
Dynamic: license-file
